deep_transit/MAP_inspection.py
deep_transit/__init__.py
deep_transit/_loss.py
deep_transit/_utils.py
deep_transit/backend.py
deep_transit/common_utils.py
deep_transit/config.py
deep_transit/dataset.py
deep_transit/dt_lightcurve.py
deep_transit/loss.py
deep_transit/model.py
deep_transit/run.py
deep_transit/train.py
deep_transit/utils.py
deep_transit/mge/__init__.py
deep_transit/mge/backend.py
deep_transit/mge/dataset.py
deep_transit/mge/loss.py
deep_transit/mge/model.py
deep_transit/mge/train.py
deep_transit/mge/utils.py
Deep_Transit-0.1.0.dist-info/LICENSE
Deep_Transit-0.1.0.dist-info/METADATA
Deep_Transit-0.1.0.dist-info/WHEEL
Deep_Transit-0.1.0.dist-info/top_level.txt
Deep_Transit-0.1.0.dist-info/RECORD
